openapi3_fuzzer/__init__.py
openapi3_fuzzer/fuzz/fuzz-array.txt
openapi3_fuzzer/fuzz/fuzz-fallback.txt
openapi3_fuzzer/fuzz/fuzz-integer.txt
openapi3_fuzzer/fuzz/fuzz-number.txt
openapi3_fuzzer/fuzz/fuzz-string.txt
test/__init__.py
test/test_fuzzer.py
openapi3_fuzzer-1.3.2.dist-info/LICENSE
openapi3_fuzzer-1.3.2.dist-info/METADATA
openapi3_fuzzer-1.3.2.dist-info/WHEEL
openapi3_fuzzer-1.3.2.dist-info/top_level.txt
openapi3_fuzzer-1.3.2.dist-info/RECORD
