Metadata-Version: 2.1
Name: openapi3-fuzzer
Version: 1.3.2
Summary: Openapi3 fuzzer
Home-page: https://github.com/vwt-digital/openapi3-fuzzer/tree/master
Author: VWT Digital
Author-email: support@vwt.digital
License: gpl-3.0
Keywords: Openapi3,fuzzer,vwt
Platform: UNKNOWN
Classifier: Programming Language :: Python :: 3.6
Classifier: License :: OSI Approved :: GNU General Public License v3 (GPLv3)
Classifier: Operating System :: OS Independent
Classifier: Intended Audience :: Developers
Classifier: Natural Language :: English
Requires-Python: >=3.6
Requires-Dist: attrs (==20.3.0)
Requires-Dist: certifi (==2020.12.5)
Requires-Dist: chardet (==4.0.0)
Requires-Dist: click (==7.1.2)
Requires-Dist: clickclick (==20.10.2)
Requires-Dist: connexion (==2.7.0)
Requires-Dist: Flask (==1.1.2)
Requires-Dist: Flask-Testing (==0.8.1)
Requires-Dist: idna (==2.10)
Requires-Dist: inflection (==0.5.1)
Requires-Dist: isodate (==0.6.0)
Requires-Dist: itsdangerous (==1.1.0)
Requires-Dist: Jinja2 (==2.11.3)
Requires-Dist: jsonschema (==3.2.0)
Requires-Dist: MarkupSafe (==1.1.1)
Requires-Dist: openapi-schema-validator (==0.1.5)
Requires-Dist: openapi-spec-validator (==0.3.0)
Requires-Dist: prance (==0.20.2)
Requires-Dist: pyrsistent (==0.17.3)
Requires-Dist: PyYAML (==5.4.1)
Requires-Dist: requests (==2.25.1)
Requires-Dist: semver (==2.13.0)
Requires-Dist: six (==1.15.0)
Requires-Dist: urllib3 (==1.26.4)
Requires-Dist: Werkzeug (==1.0.1)
